{
  "id": "00000000-0000-0000-0000-000000000000",
  "prevId": "",
  "version": "7",
  "dialect": "postgresql",
  "tables": {
    "public.contact_submissions": {
      "name": "contact_submissions",
      "schema": "",
      "columns": {
        "id": {
          "name": "id",
          "type": "uuid",
          "primaryKey": true,
          "notNull": true,
          "default": "gen_random_uuid()"
        },
        "first_name": {
          "name": "first_name",
          "type": "text",
          "primaryKey": false,
          "notNull": true
        },
        "last_name": {
          "name": "last_name",
          "type": "text",
          "primaryKey": false,
          "notNull": true
        },
        "email": {
          "name": "email",
          "type": "text",
          "primaryKey": false,
          "notNull": true
        },
        "message": {
          "name": "message",
          "type": "text",
          "primaryKey": false,
          "notNull": true
        },
        "created_at": {
          "name": "created_at",
          "type": "timestamp with time zone",
          "primaryKey": false,
          "notNull": true,
          "default": "now()"
        }
      },
      "indexes": {},
      "foreignKeys": {},
      "compositePrimaryKeys": {},
      "uniqueConstraints": {},
      "checkConstraints": {},
      "policies": {},
      "isRLSEnabled": true
    },
    "public.artworks": {
      "name": "artworks",
      "schema": "",
      "columns": {
        "id": {
          "name": "id",
          "type": "uuid",
          "primaryKey": true,
          "notNull": true,
          "default": "gen_random_uuid()"
        },
        "title": {
          "name": "title",
          "type": "text",
          "primaryKey": false,
          "notNull": true
        },
        "description": {
          "name": "description",
          "type": "text",
          "primaryKey": false,
          "notNull": false
        },
        "process": {
          "name": "process",
          "type": "text",
          "primaryKey": false,
          "notNull": false
        },
        "medium": {
          "name": "medium",
          "type": "text",
          "primaryKey": false,
          "notNull": false
        },
        "dimensions": {
          "name": "dimensions",
          "type": "text",
          "primaryKey": false,
          "notNull": false
        },
        "year": {
          "name": "year",
          "type": "text",
          "primaryKey": false,
          "notNull": false
        },
        "price": {
          "name": "price",
          "type": "integer",
          "primaryKey": false,
          "notNull": false
        },
        "image_url": {
          "name": "image_url",
          "type": "text",
          "primaryKey": false,
          "notNull": true
        },
        "stock": {
          "name": "stock",
          "type": "integer",
          "primaryKey": false,
          "notNull": true,
          "default": 1
        },
        "featured": {
          "name": "featured",
          "type": "boolean",
          "primaryKey": false,
          "notNull": true,
          "default": false
        },
        "created_at": {
          "name": "created_at",
          "type": "timestamp with time zone",
          "primaryKey": false,
          "notNull": true,
          "default": "now()"
        },
        "images": {
          "name": "images",
          "type": "text[]",
          "primaryKey": false,
          "notNull": false
        },
        "collection_id": {
          "name": "collection_id",
          "type": "uuid",
          "primaryKey": false,
          "notNull": false
        },
        "tagline": {
          "name": "tagline",
          "type": "text",
          "primaryKey": false,
          "notNull": false
        },
        "visible": {
          "name": "visible",
          "type": "boolean",
          "primaryKey": false,
          "notNull": false,
          "default": true
        },
        "slug": {
          "name": "slug",
          "type": "text",
          "primaryKey": false,
          "notNull": false
        }
      },
      "indexes": {
        "artworks_collection_id_idx": {
          "name": "artworks_collection_id_idx",
          "columns": [
            {
              "expression": "collection_id",
              "asc": true,
              "nulls": "last",
              "opclass": "uuid_ops",
              "isExpression": false
            }
          ],
          "isUnique": false,
          "concurrently": false,
          "method": "btree",
          "with": {}
        },
        "artworks_featured_idx": {
          "name": "artworks_featured_idx",
          "columns": [
            {
              "expression": "featured",
              "asc": true,
              "nulls": "last",
              "opclass": "bool_ops",
              "isExpression": false
            }
          ],
          "isUnique": false,
          "concurrently": false,
          "method": "btree",
          "with": {}
        }
      },
      "foreignKeys": {
        "artworks_collection_id_fkey": {
          "name": "artworks_collection_id_fkey",
          "tableFrom": "artworks",
          "tableTo": "collections",
          "schemaTo": "public",
          "columnsFrom": [
            "collection_id"
          ],
          "columnsTo": [
            "id"
          ],
          "onDelete": "no action",
          "onUpdate": "no action"
        }
      },
      "compositePrimaryKeys": {},
      "uniqueConstraints": {},
      "checkConstraints": {},
      "policies": {
        "artworks: public read": {
          "name": "artworks: public read",
          "as": "PERMISSIVE",
          "for": "SELECT",
          "to": [
            "public"
          ],
          "using": "true"
        }
      },
      "isRLSEnabled": true
    },
    "public.orders": {
      "name": "orders",
      "schema": "",
      "columns": {
        "id": {
          "name": "id",
          "type": "uuid",
          "primaryKey": true,
          "notNull": true,
          "default": "gen_random_uuid()"
        },
        "artwork_id": {
          "name": "artwork_id",
          "type": "uuid",
          "primaryKey": false,
          "notNull": false
        },
        "stripe_session_id": {
          "name": "stripe_session_id",
          "type": "text",
          "primaryKey": false,
          "notNull": true
        },
        "amount_cents": {
          "name": "amount_cents",
          "type": "integer",
          "primaryKey": false,
          "notNull": false
        },
        "customer_email": {
          "name": "customer_email",
          "type": "text",
          "primaryKey": false,
          "notNull": false
        },
        "status": {
          "name": "status",
          "type": "text",
          "primaryKey": false,
          "notNull": true,
          "default": "'completed'"
        },
        "created_at": {
          "name": "created_at",
          "type": "timestamp with time zone",
          "primaryKey": false,
          "notNull": true,
          "default": "now()"
        },
        "customer_name": {
          "name": "customer_name",
          "type": "text",
          "primaryKey": false,
          "notNull": false
        },
        "customer_phone": {
          "name": "customer_phone",
          "type": "text",
          "primaryKey": false,
          "notNull": false
        },
        "shipping_name": {
          "name": "shipping_name",
          "type": "text",
          "primaryKey": false,
          "notNull": false
        },
        "shipping_line1": {
          "name": "shipping_line1",
          "type": "text",
          "primaryKey": false,
          "notNull": false
        },
        "shipping_line2": {
          "name": "shipping_line2",
          "type": "text",
          "primaryKey": false,
          "notNull": false
        },
        "shipping_city": {
          "name": "shipping_city",
          "type": "text",
          "primaryKey": false,
          "notNull": false
        },
        "shipping_state": {
          "name": "shipping_state",
          "type": "text",
          "primaryKey": false,
          "notNull": false
        },
        "shipping_postal_code": {
          "name": "shipping_postal_code",
          "type": "text",
          "primaryKey": false,
          "notNull": false
        },
        "shipping_country": {
          "name": "shipping_country",
          "type": "text",
          "primaryKey": false,
          "notNull": false
        },
        "payment_method": {
          "name": "payment_method",
          "type": "text",
          "primaryKey": false,
          "notNull": false,
          "default": "''"
        },
        "message": {
          "name": "message",
          "type": "text",
          "primaryKey": false,
          "notNull": false,
          "default": "''"
        }
      },
      "indexes": {
        "orders_artwork_id_idx": {
          "name": "orders_artwork_id_idx",
          "columns": [
            {
              "expression": "artwork_id",
              "asc": true,
              "nulls": "last",
              "opclass": "uuid_ops",
              "isExpression": false
            }
          ],
          "isUnique": false,
          "concurrently": false,
          "method": "btree",
          "with": {}
        },
        "orders_stripe_id_idx": {
          "name": "orders_stripe_id_idx",
          "columns": [
            {
              "expression": "stripe_session_id",
              "asc": true,
              "nulls": "last",
              "opclass": "text_ops",
              "isExpression": false
            }
          ],
          "isUnique": false,
          "concurrently": false,
          "method": "btree",
          "with": {}
        }
      },
      "foreignKeys": {
        "orders_artwork_id_fkey": {
          "name": "orders_artwork_id_fkey",
          "tableFrom": "orders",
          "tableTo": "artworks",
          "schemaTo": "public",
          "columnsFrom": [
            "artwork_id"
          ],
          "columnsTo": [
            "id"
          ],
          "onDelete": "set null",
          "onUpdate": "no action"
        }
      },
      "compositePrimaryKeys": {},
      "uniqueConstraints": {
        "orders_session_artwork_unique": {
          "columns": [
            "artwork_id",
            "stripe_session_id"
          ],
          "nullsNotDistinct": false,
          "name": "orders_session_artwork_unique"
        }
      },
      "checkConstraints": {},
      "policies": {},
      "isRLSEnabled": true
    },
    "public.collections": {
      "name": "collections",
      "schema": "",
      "columns": {
        "id": {
          "name": "id",
          "type": "uuid",
          "primaryKey": true,
          "notNull": true,
          "default": "gen_random_uuid()"
        },
        "slug": {
          "name": "slug",
          "type": "text",
          "primaryKey": false,
          "notNull": true
        },
        "name": {
          "name": "name",
          "type": "text",
          "primaryKey": false,
          "notNull": true
        },
        "description_collection": {
          "name": "description_collection",
          "type": "text",
          "primaryKey": false,
          "notNull": false
        },
        "cover_image_url": {
          "name": "cover_image_url",
          "type": "text",
          "primaryKey": false,
          "notNull": false
        },
        "sort_order": {
          "name": "sort_order",
          "type": "integer",
          "primaryKey": false,
          "notNull": false,
          "default": 0
        },
        "created_at": {
          "name": "created_at",
          "type": "timestamp with time zone",
          "primaryKey": false,
          "notNull": false,
          "default": "now()"
        },
        "tagline": {
          "name": "tagline",
          "type": "text",
          "primaryKey": false,
          "notNull": false
        },
        "hero_image": {
          "name": "hero_image",
          "type": "text",
          "primaryKey": false,
          "notNull": false
        },
        "visible": {
          "name": "visible",
          "type": "boolean",
          "primaryKey": false,
          "notNull": false,
          "default": true
        },
        "description": {
          "name": "description",
          "type": "text",
          "primaryKey": false,
          "notNull": false
        },
        "process": {
          "name": "process",
          "type": "text",
          "primaryKey": false,
          "notNull": false
        },
        "medium": {
          "name": "medium",
          "type": "text",
          "primaryKey": false,
          "notNull": false
        },
        "year": {
          "name": "year",
          "type": "text",
          "primaryKey": false,
          "notNull": false
        },
        "price": {
          "name": "price",
          "type": "numeric",
          "primaryKey": false,
          "notNull": false
        }
      },
      "indexes": {},
      "foreignKeys": {},
      "compositePrimaryKeys": {},
      "uniqueConstraints": {
        "collections_slug_key": {
          "columns": [
            "slug"
          ],
          "nullsNotDistinct": false,
          "name": "collections_slug_key"
        }
      },
      "checkConstraints": {},
      "policies": {
        "Public read": {
          "name": "Public read",
          "as": "PERMISSIVE",
          "for": "SELECT",
          "to": [
            "public"
          ],
          "using": "true"
        }
      },
      "isRLSEnabled": true
    }
  },
  "enums": {},
  "schemas": {},
  "sequences": {},
  "roles": {},
  "policies": {},
  "views": {},
  "_meta": {
    "schemas": {},
    "tables": {},
    "columns": {}
  },
  "internal": {
    "tables": {
      "artworks": {
        "columns": {
          "images": {
            "isArray": true,
            "dimensions": 1,
            "rawType": "text"
          }
        }
      }
    }
  }
}